decorator_example.py
kraken_sockets/__init__.py
kraken_sockets/api.py
schema/__init__.py
schema/requests/__init__.py
schema/requests/admin_requests.py
schema/requests/base_requests.py
schema/requests/market_data_requests.py
schema/requests/user_data_requests.py
schema/responses/__init__.py
schema/responses/admin_responses.py
schema/responses/base_responses.py
schema/responses/market_data_responses.py
schema/responses/subscription_responses.py
tests/__init__.py
kraken_sockets-0.1.2.dist-info/METADATA
kraken_sockets-0.1.2.dist-info/WHEEL
kraken_sockets-0.1.2.dist-info/top_level.txt
kraken_sockets-0.1.2.dist-info/RECORD
