Metadata-Version: 2.4
Name: kraken-sockets
Version: 0.1.2
Summary: Easy Kraken Websockets. Just wrap your triggers and build.
Requires-Python: >=3.13
Requires-Dist: loguru>=0.7.3
Requires-Dist: python-dotenv>=1.1.1
Requires-Dist: requests>=2.32.5
Requires-Dist: websockets>=15.0.1
